plexmediafixup/__init__.py
plexmediafixup/cli.py
plexmediafixup/fixup.py
plexmediafixup/version.py
plexmediafixup/fixups/__init__.py
plexmediafixup/fixups/preserve_collections.py
plexmediafixup/fixups/sync_sort_title.py
plexmediafixup/fixups/sync_title.py
plexmediafixup/fixups/video_genre_cleanup.py
plexmediafixup/utils/__init__.py
plexmediafixup/utils/config_file.py
plexmediafixup/utils/json_schema_defaults.py
plexmediafixup/utils/smart_formatter.py
plexmediafixup/utils/unicode.py
plexmediafixup/utils/watcher.py
plexmediafixup-0.6.0.dist-info/LICENSE
plexmediafixup-0.6.0.dist-info/METADATA
plexmediafixup-0.6.0.dist-info/WHEEL
plexmediafixup-0.6.0.dist-info/entry_points.txt
plexmediafixup-0.6.0.dist-info/top_level.txt
plexmediafixup-0.6.0.dist-info/zip-safe
plexmediafixup-0.6.0.dist-info/RECORD
