Metadata-Version: 2.1
Name: plexmediafixup
Version: 0.6.0
Summary: Run configurable fixups against the media database of a Plex Media Server
Home-page: https://github.com/andy-maier/plexmediafixup
Author: Andreas Maier
Author-email: andreas.r.maier@gmx.de
Maintainer: Andreas Maier
Maintainer-email: andreas.r.maier@gmx.de
License: Apache Software License 2.0
Platform: any
Classifier: Development Status :: 4 - Beta
Classifier: Environment :: Console
Classifier: Intended Audience :: End Users/Desktop
Classifier: License :: OSI Approved :: Apache Software License
Classifier: Operating System :: OS Independent
Classifier: Programming Language :: Python :: 3
Classifier: Programming Language :: Python :: 3.5
Classifier: Programming Language :: Python :: 3.6
Classifier: Programming Language :: Python :: 3.7
Classifier: Programming Language :: Python :: 3.8
Classifier: Topic :: Multimedia
Classifier: Topic :: Utilities
Requires-Python: >=3.5
License-File: LICENSE
Requires-Dist: PlexAPI (>=3.2.0)
Requires-Dist: yamlloader (>=0.5.0)
Requires-Dist: jsonschema (>=3.0.0)
Requires-Dist: six (>=1.11.0)
Requires-Dist: ffmpy (>=0.2.0)
Requires-Dist: unidecode (>=1.1.0)
Requires-Dist: mock (>=2.0.0)
